django_keycloak/__init__.py
django_keycloak/admin.py
django_keycloak/apps.py
django_keycloak/authentication.py
django_keycloak/backends.py
django_keycloak/models.py
django_keycloak/tools.py
django_keycloak/urls.py
django_keycloak/views.py
django_keycloak/migrations/0001_initial.py
django_keycloak/migrations/0002_delete_keycloakuser.py
django_keycloak/migrations/__init__.py
django_keycloak_admin-0.0.5.dist-info/METADATA
django_keycloak_admin-0.0.5.dist-info/WHEEL
django_keycloak_admin-0.0.5.dist-info/top_level.txt
django_keycloak_admin-0.0.5.dist-info/RECORD
