Metadata-Version: 2.1
Name: django-keycloak-admin
Version: 0.0.5
Summary: Keycloak admin and REST auth.
Author-email: Erik Polzin <eriktpol@gmail.com>
Project-URL: Homepage, https://github.com/ErikPolzin/django-keycloak
Project-URL: Issues, https://github.com/ErikPolzin/django-keycloak/issues
Classifier: Programming Language :: Python :: 3
Classifier: License :: OSI Approved :: MIT License
Classifier: Operating System :: OS Independent
Requires-Python: >=3.8
Requires-Dist: python-keycloak>=4.0.0
Requires-Dist: Django>=5.0.0
Requires-Dist: djangorestframework>=3.0.0
Provides-Extra: build
Requires-Dist: build; extra == "build"
Requires-Dist: twine; extra == "build"
Provides-Extra: dev
Requires-Dist: pip-tools; extra == "dev"
Requires-Dist: bumpver; extra == "dev"
Requires-Dist: pytest; extra == "dev"
Requires-Dist: pytest-django; extra == "dev"
